helloPKG/__init__.py
helloPKG/hello.py
hunauchenym_hello-1.2.dist-info/METADATA
hunauchenym_hello-1.2.dist-info/WHEEL
hunauchenym_hello-1.2.dist-info/top_level.txt
hunauchenym_hello-1.2.dist-info/RECORD
