Metadata-Version: 2.1
Name: hunauchenym-hello
Version: 1.2
Summary: hello setuptools
Home-page: https://github.com/chenym/hello
Author: chenym
Author-email: hunauchenym@qq.com
License: MIT
Platform: UNKNOWN
